{"elever":310,"lararbehorighet":74.6,"programs":[{"c":"BA25","n":30,"a":131.3,"am":80,"ay":"2025","g":12.8,"ge":13.6,"e":null,"h":null,"ns":3,"ne":null,"nm":null},{"c":"EE25","n":100,"a":172,"am":97.5,"ay":"2025","g":11.9,"ge":13,"e":67.9,"h":null,"ns":8.5,"ne":12.3,"nm":5.7},{"c":"FR25","n":20,"a":150,"am":87.5,"ay":"2025","g":null,"ge":null,"e":null,"h":null,"ns":null,"ne":null,"nm":null},{"c":"FT25","n":30,"a":171.7,"am":92.5,"ay":"2025","g":11.6,"ge":12.8,"e":null,"h":null,"ns":null,"ne":null,"nm":1.3},{"c":"HV25","n":null,"a":null,"am":null,"ay":null,"g":12.8,"ge":13.5,"e":84.6,"h":null,"ns":null,"ne":null,"nm":1.3},{"c":"NB25","n":10,"a":232.5,"am":232.5,"ay":"2025","g":null,"ge":null,"e":null,"h":null,"ns":null,"ne":null,"nm":null}]}