{"elever":220,"lararbehorighet":82,"programs":[{"c":"EK25","n":80,"a":208.9,"am":172.5,"ay":"2025","g":null,"ge":null,"e":null,"h":null,"ns":null,"ne":13.9,"nm":7,"sa":{"2025":208.9},"se":{},"sg":{}},{"c":"NA25","n":40,"a":229.8,"am":167.5,"ay":"2025","g":null,"ge":null,"e":null,"h":null,"ns":null,"ne":12.2,"nm":null,"sa":{"2025":229.8},"se":{},"sg":{}},{"c":"SA25","n":80,"a":195.9,"am":145,"ay":"2025","g":null,"ge":null,"e":null,"h":null,"ns":null,"ne":11.4,"nm":0.5,"sa":{"2025":195.9},"se":{},"sg":{}},{"c":"TE25","n":30,"a":219.4,"am":200,"ay":"2025","g":null,"ge":null,"e":null,"h":null,"ns":null,"ne":13.5,"nm":null,"sa":{"2025":219.4},"se":{},"sg":{}}]}