{"elever":250,"lararbehorighet":68.2,"programs":[{"c":"BF25","n":10,"a":170.8,"am":115,"ay":"2025","g":null,"ge":null,"e":null,"h":null,"ns":10.4,"ne":null,"nm":null,"sa":{"2025":170.8},"se":{},"sg":{}},{"c":"EK25","n":60,"a":221.9,"am":175,"ay":"2025","g":14.9,"ge":14.9,"e":57.9,"h":100,"ns":14.9,"ne":13,"nm":10.8,"sa":{"2025":221.9},"se":{"2022/23":57.9,"2019/20":75,"2018/19":90.9},"sg":{"2024/25":14.9,"2023/24":14.5,"2022/23":14.2,"2021/22":14.7,"2020/21":14.7}},{"c":"FL25","n":40,"a":206.9,"am":172.5,"ay":"2025","g":13.9,"ge":13.9,"e":null,"h":90.9,"ns":9.6,"ne":null,"nm":10.4,"sa":{"2025":206.9},"se":{},"sg":{"2023/24":13.9}},{"c":"FT25","n":80,"a":230.1,"am":195,"ay":"2025","g":13.2,"ge":13.2,"e":76.5,"h":null,"ns":10.4,"ne":13,"nm":10.4,"sa":{"2025":230.1},"se":{"2022/23":76.5,"2021/22":85,"2020/21":90.9,"2019/20":87.5,"2018/19":85},"sg":{"2024/25":13.2,"2023/24":12.5,"2022/23":13.7,"2021/22":13.3,"2020/21":13.6}},{"c":"NA25","n":30,"a":245,"am":197.5,"ay":"2025","g":14.8,"ge":null,"e":null,"h":null,"ns":11.9,"ne":16.3,"nm":14.4,"sa":{"2025":245},"se":{},"sg":{"2024/25":14.8}},{"c":"SA25","n":30,"a":216,"am":180,"ay":"2025","g":14.8,"ge":14.8,"e":73.3,"h":100,"ns":14,"ne":13.9,"nm":10.7,"sa":{"2025":216},"se":{"2021/22":73.3},"sg":{"2023/24":14.8}}]}