{"elever":520,"lararbehorighet":79.7,"programs":[{"c":"EE25","n":130,"a":177.1,"am":82.5,"ay":"2025","g":12.4,"ge":12.7,"e":88.2,"h":22.1,"ns":8.9,"ne":14.1,"nm":5.8,"sa":{"2025":177.1},"se":{"2022/23":88.2,"2021/22":73.1,"2020/21":81,"2019/20":88.5,"2018/19":66.7},"sg":{"2024/25":12.4,"2023/24":13.3,"2022/23":13,"2021/22":12.7,"2020/21":12.7}},{"c":"EK25","n":30,"a":239.3,"am":197.5,"ay":"2025","g":null,"ge":null,"e":null,"h":null,"ns":null,"ne":null,"nm":null,"sa":{"2025":239.3},"se":{},"sg":{}},{"c":"FR25","n":10,"a":145.8,"am":82.5,"ay":"2025","g":null,"ge":null,"e":null,"h":null,"ns":null,"ne":null,"nm":null,"sa":{"2025":145.8},"se":{},"sg":{}},{"c":"FS25","n":40,"a":171.1,"am":90,"ay":"2025","g":null,"ge":null,"e":null,"h":null,"ns":null,"ne":9.2,"nm":null,"sa":{"2025":171.1},"se":{},"sg":{}},{"c":"FT25","n":30,"a":178.3,"am":132.5,"ay":"2025","g":12.7,"ge":12.7,"e":90.9,"h":null,"ns":5.8,"ne":13.1,"nm":null,"sa":{"2025":178.3},"se":{"2018/19":90.9},"sg":{"2024/25":12.7,"2023/24":11.8,"2022/23":12.5,"2021/22":12.6,"2020/21":12.5}},{"c":"HV25","n":null,"a":null,"am":null,"ay":null,"g":12.7,"ge":14,"e":null,"h":null,"ns":6,"ne":11.5,"nm":null,"sa":{},"se":{},"sg":{"2023/24":12.7,"2021/22":13.5}},{"c":"IMV","n":50,"a":null,"am":null,"ay":null,"g":null,"ge":null,"e":70.6,"h":null,"ns":null,"ne":null,"nm":null,"sa":{},"se":{"2019/20":70.6},"sg":{}},{"c":"SA25","n":30,"a":210.8,"am":142.5,"ay":"2025","g":null,"ge":null,"e":null,"h":null,"ns":null,"ne":null,"nm":null,"sa":{"2025":210.8},"se":{},"sg":{}},{"c":"VO25","n":30,"a":216.5,"am":97.5,"ay":"2025","g":null,"ge":null,"e":null,"h":null,"ns":null,"ne":null,"nm":null,"sa":{"2025":216.5},"se":{},"sg":{}}]}